COPYING
MANIFEST.in
README.rst
pyofss
setup.py
pyofss_gui/__init__.py
pyofss_gui/gui_domain.py
pyofss_gui/gui_fibre.py
pyofss_gui/gui_gaussian.py
pyofss_gui/gui_group.py
pyofss_gui/gui_plotter.py
pyofss_gui/gui_sech.py
pyofss_gui/gui_system.py
pyofss_gui/helpers.py
pyofss_gui.egg-info/PKG-INFO
pyofss_gui.egg-info/SOURCES.txt
pyofss_gui.egg-info/dependency_links.txt
pyofss_gui.egg-info/requires.txt
pyofss_gui.egg-info/top_level.txt