Metadata-Version: 1.1
Name: pyofss-gui
Version: 0.2
Summary: Graphical user interface for pyofss
Home-page: http://curvedthoughts.com/pyofss
Author: David Bolt (daibo)
Author-email: djb@curvedthoughts.com
License: GNU GPL
Download-URL: http://pypi.python.org/pypi/pyofss-gui
Keywords: photonic,simulation,fiber,fibre,optical
Platform: POSIX
Classifier: Development Status :: 3 - Alpha
Classifier: Environment :: X11 Applications :: Qt
Classifier: Intended Audience :: Science/Research
Classifier: License :: OSI Approved :: GNU General Public License v3 (GPLv3)
Classifier: Natural Language :: English
Classifier: Operating System :: POSIX :: Linux
Classifier: Programming Language :: Python :: 2.6
Classifier: Programming Language :: Python :: 2.7
Classifier: Topic :: Scientific/Engineering :: Physics
